LICENSE.txt
MANIFEST.in
requirements.txt
setup.cfg
setup.py
datatypes/__init__.py
datatypes/core.py
datatypes/exceptions.py
datatypes/json_serializer.py
datatypes/validators/__init__.py
datatypes/validators/address_validator.py
datatypes/validators/common_validators.py
datatypes/validators/deed_validator.py
datatypes/validators/entry_validator.py
datatypes/validators/geo_json_validator.py
datatypes/validators/iso_country_code_validator.py
datatypes/validators/ogc_urn_validator.py
datatypes/validators/postcode_validator.py
datatypes/validators/price_validator.py
datatypes/validators/property_description_validator.py
datatypes/validators/proprietor_validator.py
datatypes/validators/proprietorship_validator.py
datatypes/validators/system_of_record_chain_message_validator.py
datatypes/validators/system_of_record_request_validator.py
datatypes/validators/title_validator.py
datatypes/voluptuous_helpers/__init__.py
datatypes/voluptuous_helpers/postcode_schema_validator.py
lrdatatypes.egg-info/PKG-INFO
lrdatatypes.egg-info/SOURCES.txt
lrdatatypes.egg-info/dependency_links.txt
lrdatatypes.egg-info/not-zip-safe
lrdatatypes.egg-info/requires.txt
lrdatatypes.egg-info/top_level.txt