Metadata-Version: 1.1
Name: lrdatatypes
Version: 0.1.1
Summary: Provides core Land Registry data types to dependent applications
Home-page: http://github.com/LandRegistry/audit-plugin
Author: Land Registry
Author-email: adam.shimali@digital.cabinet-office.gov.uk
License: MIT
Download-URL: http://github.com/LandRegistry/audit-plugin/tarball/alpha
Keywords: validation
Platform: any
Classifier: Development Status :: 3 - Alpha
Classifier: Environment :: Web Environment
Classifier: Programming Language :: Python :: 2.7
